MANIFEST.in
README.md
README.rst
setup.py
django_sape3.egg-info/PKG-INFO
django_sape3.egg-info/SOURCES.txt
django_sape3.egg-info/dependency_links.txt
django_sape3.egg-info/top_level.txt
sape/__init__.py
sape/sape_client.py
sape/management/__init__.py
sape/management/commands/__init__.py
sape/management/commands/sape.py
sape/templates/sape/block.html
sape/templates/sape/links.html
sape/templatetags/__init__.py
sape/templatetags/sape.py